cogie/__init__.py
cogie/config/__init__.py
cogie/core/__init__.py
cogie/core/datable.py
cogie/core/datableset.py
cogie/core/logger.py
cogie/core/loss.py
cogie/core/metrics.py
cogie/core/predictor.py
cogie/core/tester.py
cogie/core/trainer.py
cogie/core/utils.py
cogie/interface/__init__.py
cogie/interface/interface.py
cogie/io/__init__.py
cogie/models/__init__.py
cogie/models/base/__init__.py
cogie/models/base/base_function.py
cogie/models/base/base_model.py
cogie/models/common/__init__.py
cogie/models/common/bert_crf.py
cogie/models/common/bert_softmax.py
cogie/models/ee/__init__.py
cogie/models/ee/bert_casee.py
cogie/models/ee/bert_ee.py
cogie/models/ee/bert_trigger.py
cogie/models/el/__init__.py
cogie/models/el/biencoder.py
cogie/models/el/blink.py
cogie/models/el/crossencoder.py
cogie/models/et/__init__.py
cogie/models/et/bert_et.py
cogie/models/et/bert_et_context.py
cogie/models/et/box4et.py
cogie/models/et/elmo_fet.py
cogie/models/fn/__init__.py
cogie/models/fn/bert_argument.py
cogie/models/fn/bert_fn.py
cogie/models/fn/bert_fn_joint.py
cogie/models/fn/bert_frame.py
cogie/models/ner/__init__.py
cogie/models/ner/bert_biaffine.py
cogie/models/ner/bert_cn_ner.py
cogie/models/ner/bert_ner.py
cogie/models/ner/flair_ner.py
cogie/models/ner/w2ner.py
cogie/models/rc/__init__.py
cogie/models/rc/bert_re.py
cogie/models/rc/bert_re_entity.py
cogie/models/re/__init__.py
cogie/models/re/bert_re.py
cogie/models/re/bert_re_entity.py
cogie/models/spo/__init__.py
cogie/models/spo/bert_spo_pfn.py
cogie/models/ws/__init__.py
cogie/models/ws/bert_ws.py
cogie/modules/__init__.py
cogie/modules/balanced_data_parallel.py
cogie/modules/box4et_modules.py
cogie/modules/decoder/__init__.py
cogie/modules/decoder/biaffine.py
cogie/modules/decoder/crf.py
cogie/modules/decoder/edge_builder.py
cogie/modules/decoder/ffn.py
cogie/modules/decoder/mlp.py
cogie/modules/decoder/node_builder.py
cogie/modules/decoder/node_edge_builder.py
cogie/modules/encoder/__init__.py
cogie/modules/encoder/cnn.py
cogie-0.1.6.dist-info/LICENSE
cogie-0.1.6.dist-info/METADATA
cogie-0.1.6.dist-info/WHEEL
cogie-0.1.6.dist-info/top_level.txt
cogie-0.1.6.dist-info/RECORD
