Metadata-Version: 2.1
Name: cogie
Version: 0.1.6
Summary: CogIE: An Information Extraction Toolkit for Bridging Text and CogNet
Home-page: https://github.com/jinzhuoran/CogIE/
Author: CogNLP Team
Author-email: zhuoran.jin@nlpr.ia.ac.cn
License: Apache
Platform: UNKNOWN
Requires-Python: >=3.7,<3.9
License-File: LICENSE
Requires-Dist: torch (>=1.7.0)
Requires-Dist: transformers (>=4.4.2)
Requires-Dist: scikit-learn (>=1.0.1)
Requires-Dist: termcolor (>=1.1.0)
Requires-Dist: colorama (>=0.4.4)
Requires-Dist: pytorch-transformers (>=1.2.0)
Requires-Dist: flair (>=0.11.3)
Requires-Dist: nltk (>=3.5)
Requires-Dist: overrides (>=3.1.0)
Requires-Dist: protobuf (>=3.20.0)
Requires-Dist: prettytable (>=2.1.0)
Requires-Dist: pyyaml (>=5.4.1)
Requires-Dist: pytorch-crf (>=0.7.0)
Requires-Dist: tensorboard (>=2.4.1)
Requires-Dist: faiss-cpu (>=1.7.2)
